dutil/__init__.py
dutil/jupyter/__init__.py
dutil/jupyter/_jupyter.py
dutil/pipeline/__init__.py
dutil/pipeline/_cached.py
dutil/pipeline/_dask.py
dutil/stats/__init__.py
dutil/stats/_quantiles.py
dutil/string/__init__.py
dutil/string/_string.py
dutil/transform/__init__.py
dutil/transform/_transform.py
dutil-0.2.24.dist-info/LICENSE
dutil-0.2.24.dist-info/METADATA
dutil-0.2.24.dist-info/WHEEL
dutil-0.2.24.dist-info/RECORD
