Metadata-Version: 2.1
Name: dutil
Version: 0.2.24
Summary: A few useful tools for data wrangling
License: Apache License, Version 2.0
Author: Mysterious Ben
Author-email: datascience@tuta.io
Requires-Python: >=3.9,<4.0
Classifier: License :: Other/Proprietary License
Classifier: Programming Language :: Python :: 3
Classifier: Programming Language :: Python :: 3.9
Classifier: Programming Language :: Python :: 3.10
Classifier: Programming Language :: Python :: 3.11
Classifier: Programming Language :: Python :: 3.12
Requires-Dist: dask[delayed] (>=2024.4.2,<2025.0.0)
Requires-Dist: dill (>=0.3.8,<0.4.0)
Requires-Dist: fuzzywuzzy (>=0.18.0,<0.19.0)
Requires-Dist: loguru (>=0.7.2,<0.8.0)
Requires-Dist: numpy (>=1.26.4,<2.0.0)
Requires-Dist: pandas (>=2.2.2,<3.0.0)
Requires-Dist: pyarrow (>=16.0.0,<17.0.0)
Requires-Dist: python-levenshtein (>=0.25.1,<0.26.0)
Requires-Dist: xxhash (>=3.4.1,<4.0.0)
